docs_reader.py
docs_reader-0.1.0.post1.dist-info/licenses/LICENSE
docs_reader-0.1.0.post1.dist-info/METADATA
docs_reader-0.1.0.post1.dist-info/WHEEL
docs_reader-0.1.0.post1.dist-info/top_level.txt
docs_reader-0.1.0.post1.dist-info/RECORD
