Metadata-Version: 2.4
Name: docs_reader
Version: 0.1.0.post1
Summary: To track previous or nearest import lines and show helper documents automatically
Author-email: Anjan Maity <anjanmaity1824@gmail.com>
License: MIT
Project-URL: Homepage, https://github.com/AnjanGitHub4/docs_reader
Project-URL: Repository, https://github.com/AnjanGitHub4/docs_reader
Keywords: docs,automation,helper
License-File: LICENSE
Dynamic: license-file
